setup.py
freezeray/__init__.py
freezeray/freeze.py
freezeray.egg-info/PKG-INFO
freezeray.egg-info/SOURCES.txt
freezeray.egg-info/dependency_links.txt
freezeray.egg-info/entry_points.txt
freezeray.egg-info/not-zip-safe
freezeray.egg-info/requires.txt
freezeray.egg-info/top_level.txt