Metadata-Version: 1.0
Name: freezeray
Version: 0.0.1
Summary: Freeze your Python package dependencies
Home-page: https://github.com/gamechanger/freezeray
Author: GameChanger
Author-email: travis@gc.io
License: MIT
Platform: UNKNOWN
